fastapi_apscheduler/__init__.py
fastapi_apscheduler/config.py
fastapi_apscheduler/routers.py
fastapi_apscheduler/scheduler.py
fastapi_apscheduler/schemas.py
fastapi_apscheduler/utils.py
fastapi_apscheduler-0.0.7.dist-info/LICENSE
fastapi_apscheduler-0.0.7.dist-info/METADATA
fastapi_apscheduler-0.0.7.dist-info/WHEEL
fastapi_apscheduler-0.0.7.dist-info/RECORD
