Metadata-Version: 2.1
Name: fastapi-apscheduler
Version: 0.0.7
Summary: Allow manage APScheduler with FastAPI router
Home-page: https://github.com/grillazz/fastapi-apscheduler
License: MIT
Author: Jakub Miazek
Author-email: the@grillazz.com
Requires-Python: >=3.8,<4.0
Classifier: License :: OSI Approved :: MIT License
Classifier: Operating System :: OS Independent
Classifier: Programming Language :: Python
Classifier: Programming Language :: Python :: 3
Classifier: Programming Language :: Python :: 3.8
Classifier: Programming Language :: Python :: 3.9
Classifier: Programming Language :: Python :: 3.10
Classifier: Programming Language :: Python :: 3.11
Classifier: Programming Language :: Python :: 3.12
Classifier: Programming Language :: Python :: 3 :: Only
Requires-Dist: APScheduler (>=3.10.4,<4.0.0)
Requires-Dist: fastapi[all] (>=0.112.0,<0.113.0)
Requires-Dist: gunicorn (>=22.0.0,<23.0.0)
Requires-Dist: typing-extensions (>=4.9.0,<5.0.0)
Project-URL: Repository, https://github.com/grillazz/fastapi-apscheduler
